glossanea/__init__.py
glossanea/__main__.py
glossanea/version.py
glossanea/cli/__init__.py
glossanea/cli/cli.py
glossanea/cli/day.py
glossanea/cli/output.py
glossanea/cli/user_input.py
glossanea/cli/weekly_review.py
glossanea/config/__init__.py
glossanea/config/app.py
glossanea/config/logging.py
glossanea/gui/__init__.py
glossanea/gui/gui.py
glossanea/structure/__init__.py
glossanea/structure/cycle.py
glossanea/structure/day.py
glossanea/structure/unit.py
glossanea/structure/user_interface.py
glossanea/structure/weekly_review.py
glossanea/utils/__init__.py
glossanea/utils/convert_data_v1_to_v2.py
glossanea/utils/data_file_loader.py
glossanea-0.0.1.dist-info/LICENSE
glossanea-0.0.1.dist-info/METADATA
glossanea-0.0.1.dist-info/WHEEL
glossanea-0.0.1.dist-info/entry_points.txt
glossanea-0.0.1.dist-info/top_level.txt
glossanea-0.0.1.dist-info/RECORD
