Metadata-Version: 2.1
Name: glossanea
Version: 0.0.1
Summary: glossanea - a program to help learning languages
Home-page: https://github.com/sunarch/glossanea
Author: András Németh (sunarch)
Author-email: sunarch@protonmail.com
Maintainer: András Németh (sunarch)
Maintainer-email: sunarch@protonmail.com
License: Mozilla Public License 2.0 (MPL 2.0)
Project-URL: Bug Tracker, https://github.com/sunarch/glossanea/issues
Keywords: glossanea,language,learn
Platform: Any
Classifier: Programming Language :: Python :: 3
Classifier: Natural Language :: English
Classifier: License :: OSI Approved :: Mozilla Public License 2.0 (MPL 2.0)
Classifier: Operating System :: OS Independent
Classifier: Development Status :: 2 - Pre-Alpha
Classifier: Environment :: Console
Classifier: Environment :: X11 Applications
Classifier: Environment :: Win32 (MS Windows)
Classifier: Intended Audience :: Education
Classifier: Intended Audience :: End Users/Desktop
Classifier: Topic :: Education
Classifier: Topic :: Education :: Testing
Classifier: Typing :: Typed
Requires-Python: >=3.9
License-File: LICENSE
Requires-Dist: xdg-base-dirs (==6.0.0)
